[
    {
        "teanslation_title": "最后的维加斯/老爆伴郎团(港)",
        "real_title": "Last Vegas",
        "time": "2013",
        "category": "喜剧",
        "language": "英语",
        "length": "105 Mins",
        "director": "乔·德特杜巴 Jon Turteltaub",
        "actors": [
            "摩根·弗里曼 Morgan Freeman  ....Archie",
            "Robert De Niro罗伯特·德尼罗 Robert De Niro  ....Paddy",
            "Michael Douglas迈克尔·道格拉斯 Michael Douglas  ....Billy",
            "Kevin Kline凯文·克莱恩 Kevin Kline",
            "Mary Steenburgen玛丽·斯汀伯根 Mary Steenburgen  ....Diana",
            "Romany Malco罗曼尼·马尔可 Romany Malco  ....Lonnie",
            "Jerry Ferrara杰瑞·费拉拉 Jerry Ferrara",
            "Roger Bart罗杰·巴特 Roger Bart  ....Maurice",
            "Dan Owens  ....Security Guard",
            "Jena Sims  ....Abby"
        ],
        "introduction": "凯文·克莱恩饰演的山姆和他的妻子生活在弗罗里达州，虽然家庭和睦，但是他腿脚不便，濒临死亡的邻居经常提醒他死期将至；摩根·弗里曼饰演的阿尔奇最近刚刚不幸中风，他严厉的儿子监控着他的一举一动；罗伯特·德尼罗饰演的派迪刚刚丧妻，每天穿着睡衣屋子里闲逛；至于道格拉斯他恐怕是最滋润在一位，全新投入他和年轻未婚妻的婚礼。这个婚礼已经成为他活下去的动力……",
        "download_url": "ftp://ygdy8:ygdy8@d006.dygod.org:1117/[阳光电影www.ygdy8.com].最后的维加斯.BD.720p.中英双字幕.rmvb",
        "content_url": "http://img226.poco.cn/mypoco/myphoto/20140124/18/66548034201401241850354100038826062_000.jpg"
    },
    {
        "real_title": "爆3俏娇娃",
        "teanslation_title": "Kick Ass Girls",
        "time": "2013",
        "category": "剧情/动作/喜剧",
        "language": "国语/粤语",
        "length": "97 Mins",
        "director": "卓韵芝 Goo-Bi GC",
        "actors": [
            "周秀娜 Chrissie Chau",
            "卢颂之 Dada Lo",
            "余晓彤 Hidy Yu",
            "徐天佑 Ting Yau Tsui",
            "童冰玉",
            "卓韵芝",
            "林佩琦",
            "喇英"
        ],
        "introduction": "故事主角的三位女孩，宝（周秀娜 Chrissie Chau饰）、娇（卢颂之 Dada Lo饰）、TT(余晓彤 Hidy Yu饰），分别面对“女人三十”、“争风吃醋”、“花痴幻想”的人生、友情、爱情等问题，为了可观报酬踏上征途，远赴马来西亚，享尽富贵荣华，原来堕入神秘女子诸葛（童冰玉 Chris Tong饰）的圈套，三人万万想不到表面简单的任务背后竟然藏着重大阴谋，而诸葛也不只是个麻烦的富婆。三女被逼参与血肉拳赛，并发现自己困于一个庞大的地下迷宫之内……在死亡边缘，她们巧妙使用高跟鞋抗敌，用内衣进击，凭着女人的智慧，睹破人贩子集团，成就一场疯狂喜剧。",
        "download_url": "ftp://ygdy8:ygdy8@d201.dygod.org:9129/[阳光电影www.ygdy8.com].爆3俏娇娃.BD.720p.国粤双语中字.mkv",
        "content_url": "http://img226.poco.cn/mypoco/myphoto/20140128/21/66548034201401282110263769827761172_000.jpg"
    },
    {
        "teanslation_title": "警察故事2013",
        "real_title": "Police Story 2013",
        "time": "2013",
        "category": "动作/爱情/犯罪",
        "language": "普通话",
        "length": "1:46:21",
        "director": "丁晟 Sheng Ding",
        "actors": [
            "成龙 Jackie Chan  ....钟文",
            "刘烨 Ye Liu  ....武江",
            "景甜 Tian Jing  ....苗苗",
            "周晓鸥 Xiaoou Zhou  ....魏小福",
            "那威 Wei Na  ....药店老板",
            "刘仪伟 Yiwei Lau  ....牛总",
            "殷桃 Tao Yin  ....妈妈桑",
            "柳海龙 Hai Long Liu  ....涛子",
            "郑晓宁 Xiaoning Zheng  ....武江父亲",
            "于荣光 Rongguang Yu  ....特警队长"
        ],
        "introduction": "刑警钟文（成龙 饰）一直忙于工作，对家庭始终怀有愧疚。这一天，搬出去独立生活的女儿苗苗（景甜饰）竟然主动相约，钟文半是兴奋，半是忐忑的赶赴约定地点。约好的地方却是一个十足新潮的酒吧，张扬的搏击风格似乎让许多俊男靓女们如痴如醉，但钟文却始终隐隐感到有些怪异。父女见面并不顺利，当得知酒吧老板武江（刘烨饰）竟是女儿的新男友时，钟文更是有些不知所措了。",
        "download_url": "ftp://ygdy8:ygdy8@d201.dygod.org:9128/[阳光电影www.ygdy8.com].警察故事2013.HD.720p.国语中字.rmvb",
        "content_url": "http://img226.poco.cn/mypoco/myphoto/20140127/20/66548034201401272032562398243105431_000.jpg"
    },
    {
        "teanslation_title": "被偷走的那五年/被偷走的时光/最后一次说爱你/倾城之泪2/被偷走的五年",
        "real_title": "The Stolen Years",
        "time": "2013",
        "category": "爱情",
        "language": "普通话",
        "length": "1h:51m:45s",
        "director": "黄真真 Babara Wong",
        "actors": [
            "白百何 Baihe Bai  ....何蔓",
            "张孝全 Hsiao-chuan Chang  ....谢宇",
            "范玮琪 Wei Chi Fan  ....路小环",
            "安心亚 Amber",
            "阿Ken Ken Lin",
            "谢君豪 Kwan-Ho Tse",
            "戴君竹 Junzhu Dai",
            "伍思凯 Sky Wu"
        ],
        "introduction": "浪漫美好的蜜月之旅，突然以一场车祸戛然而止。曾经沉浸在无上幸福中的何蔓（白百何饰）从昏迷中醒来，却从姐姐何琪（戴君竹饰）那里得知自己已经和深爱的老公谢宇（张孝全饰）离婚的消息。原来她不久前刚刚出了一场车祸，导致忘记了过去五年间发生过的所有事情，最后的记忆只停留在2007年蜜月旅行的梦幻时刻。五年的时间，身边的人和整个世界都发生了太多太多的事情，她痛哭流涕，找到已有新女友的谢宇渴望找回往昔的记忆。",
        "download_url": "ftp://ygdy8:ygdy8@d006.dygod.org:1116/[阳光电影www.ygdy8.com].被偷走的那五年.BD.720p.国语中字.rmvb",
        "content_url": "http://img226.poco.cn/mypoco/myphoto/20140127/20/66548034201401272032562398243105431_001.jpg"
    },
    {
        "real_title": "僵尸/七日重生",
        "teanslation_title": "Rigor Mortis",
        "time": "2013",
        "category": "动作/剧情/恐怖",
        "language": "国语/粤语",
        "length": "134 Mins",
        "director": "麦浚龙 Juno Mak",
        "actors": [
            "钱小豪 Siu-hou Chin  ....Chin, Siu-Ho",
            "陈友 Anthony Chan",
            "惠英红 Kara Hui",
            "楼南光 Billy Lau",
            "鲍起静 Hee Ching Paw  ....Auntie Mui (as Nina Paw)",
            "卢海鹏 Hoi-Pang Lo",
            "邵音音 Yam Yam Siu",
            "吴耀汉 Richard Ng",
            "钟发 Fat Chung"
        ],
        "introduction": "故事讲述了80年代知名动作影星小豪（钱小豪饰）曾经凭《僵尸先生》饰演“僵尸猎人”红极一时，可惜年事渐长，风光不再，私生活上也是极为混乱潦倒，无奈迁入公共屋凶宅单位2442居住，并决定在凶宅内了结自己的生命，但却遇上一些改变他命运的人，包括隐世的末代天师阿友（陈友饰）、有家归不得、受过严重心灵创伤的神经病杨凤（惠英红饰）、乐于助人、但在家中私藏了一具棺材的屋师奶梅姨（鲍起静饰）等，更惊爆僵尸肆虐杀人事件，小豪与阿友再次面对凶猛僵尸袭击，必须设法合力降服这具疯狂嗜血的不死之身…",
        "download_url": "ftp://ygdy8:ygdy8@d201.dygod.org:9127/[阳光电影www.ygdy8.com].僵尸.BD.720p.国粤双语中字.mkv",
        "content_url": "http://img226.poco.cn/mypoco/myphoto/20140126/21/66548034201401262113433507410313211_000.jpg"
    },
    {
        "teanslation_title": "一场风花雪月的事",
        "real_title": "Crimes.of.Passion",
        "time": "2013",
        "category": "动作/爱情/犯罪",
        "language": "普通话/英语/韩语/粤语",
        "length": "1:40:09",
        "director": "高群书 Qunshu Gao",
        "actors": [
            "杨颖 Angela Baby  ....吕月月",
            "黄晓明 Xiaoming Huang  ....薛宇",
            "在熙 Hyun-kyoon Lee  ....正熙",
            "巍子 WeiZi苏青 Qing Su",
            "许俊豪 Joon-ho Hur  ....金正泰"
        ],
        "introduction": "08年夏天，失踪多年的国宝——金佛，重现在韩国头号黑帮——金氏家族之手。警方在金氏次子正熙（在熙饰）潜入深圳境内避难时，安排女警吕月月（Angelababy饰）以全程保护正熙之名追查金佛下落，两人经历了险象环生的黑帮追杀后情愫暗生，导致月月与警察男友薛宇（黄晓明饰）的关系变得紧张。正熙答应配合警方的行动，却在哥哥正泰的安排下，携金佛潜逃。正熙失踪的日子里，月月与薛宇逐渐重修就好，正熙突然出现将金佛归公，月月陷入在正熙和薛宇之间选择的两难境地……",
        "download_url": "ftp://ygdy8:ygdy8@d006.dygod.org:1115/[阳光电影www.ygdy8.com].一场风花雪月的事.HD.720p.国语中字.rmvb",
        "content_url": "http://img226.poco.cn/mypoco/myphoto/20140126/21/66548034201401262113433507410313211_001.jpg"
    },
    {
        "teanslation_title": "达拉斯买家俱乐部/续命枭雄(港)",
        "real_title": "Dallas Buyers Club",
        "time": "2013",
        "category": "传记/剧情/历史",
        "language": "英语",
        "length": "117 Mins",
        "director": "让-马克·瓦雷 Jean-Marc Vallée",
        "actors": [
            "马修·麦康纳 Matthew McConaughey  ....Ron Woodroof",
            "珍妮弗·加纳 Jennifer Garner  ....Dr. Eve Saks",
            "杰瑞德·莱托 Jared Leto  ....Rayon",
            "史蒂夫·茨恩 Steve Zahn",
            "达拉斯·罗伯特斯 Dallas Roberts  ....David Wayne",
            "凯文·兰金 Kevin Rankin  ....T.j",
            "丹尼斯·欧哈拉 Denis O'Hare",
            "格里芬·邓恩 Griffin Dunne",
            "Jane McNeill  ....Francine Suskind",
            "Juliet Reeves  ....Rodeo Girl"
        ],
        "introduction": "本片根据罗恩·伍德鲁夫Ron Woodroof的真实经历改编。这是一个关于绝症患者努力求生的故事，也是一个关于抗争的故事。1986年的达拉斯，罗恩(Ron Woodroof)(马修·麦康纳 Matthew McConaughey饰演)被确证为艾滋病晚期，他并被告知只剩下30天的生命，他所服用的药剂AZT是当时FDA(美国食品药品管理局)唯一合法批准上市的一种艾滋病治疗药物，但遗憾的是这药物让他病情恶化的更快。为了能够活下去，他开始研究各类未受当局批准的抗艾滋病药物和替代疗法，甚至非法走私来自全世界各地的各种抗艾滋病病药物，不少病人找到了罗恩所在的医院，并寄希望于罗恩能找到替代AZT的其他药物以及更有效的治疗方式，在罗恩的医生Eve Saks(詹妮弗·加纳 Jennifer Garner饰演)以及一个变性异装癖病友Rayon(杰瑞德·莱托 Jared Leto饰演)的帮助下，罗恩就这样不经意间成立了一个叫“达拉斯买家俱乐部”的组织，为俱乐部会员提供更多替代AZT的药物和疗法，该俱乐部迅速受到全国各地病友的推崇，会员人数和药物需求大幅增长，这引起了FDA和制药商对罗恩的关注，并对其多方阻挠。罗恩最终于1992年9月12日去世，从他被确诊只剩30天生命之日直至去世时他一共存活了7年多，在这2557天中，他一直坚持不懈的与病魔、与FDA及制药商进行异常艰苦的抗争。",
        "download_url": "ftp://ygdy8:ygdy8@d201.dygod.org:9126/[阳光电影www.ygdy8.com].达拉斯买家俱乐部.BD.720p.中英双字幕.rmvb",
        "content_url": "http://img226.poco.cn/mypoco/myphoto/20140125/22/66548034201401252230392583950226153_001.jpg"
    },
    {
        "teanslation_title": "污垢",
        "real_title": "Filth",
        "time": "2013",
        "category": "剧情/喜剧/犯罪",
        "language": "英语",
        "length": "97 min",
        "director": "乔·拜尔德 Jon S. Baird",
        "actors": [
            "詹姆斯·麦卡沃伊 James McAvoy  ....Bruce Robertson",
            "杰米·贝尔 Jamie Bell  ....Ray Lennox",
            "吉姆·布劳德本特 Jim Broadbent  ....Dr. Rossi",
            "伊莫珍·波茨 Imogen Poots  ....Amanda Drummond",
            "琼安·弗洛加特 Joanne Froggatt  ....Mary",
            "埃迪·马森 Eddie Marsan  ....Bladesey",
            "伊蒙·艾略特 Emun Elliot  ....Peter Inglis",
            "凯特·迪基 Kate Dickie  ....Chrissie",
            "雪莉·亨德森 Shirley Henderson  ....Bunty",
            "Ron Donachie  ....Hector"
        ],
        "introduction": "改编自《猜火车》作者埃文·威尔什的同名小说。《污垢》讲述了一个发生在爱丁堡邪恶警察身上的故事。该警察脾气暴虐，作恶多端，而且还涉及未 成 年人的性 交 易。",
        "download_url": "ftp://ygdy8:ygdy8@d006.dygod.org:1114/[阳光电影www.ygdy8.com].污垢.BD.720p.中英双字幕.rmvb",
        "content_url": "http://img226.poco.cn/mypoco/myphoto/20140125/22/66548034201401252230392583950226153_000.jpg"
    },
    {
        "teanslation_title": "扫毒/变役",
        "real_title": "The White Storm",
        "time": "2013",
        "category": "剧情/动作/悬疑/犯罪",
        "language": "普通话",
        "length": "2h 13mn",
        "director": "刘存明 Cunming Liu",
        "actors": [
            "刘青云 Ching Wan Lau  ....马昊天",
            "古天乐 Louis Koo  ....苏建秋",
            "张家辉 Nick Cheung  ....张子伟",
            "卢海鹏 Hoi-Pang Lo  ....八面佛",
            "宝儿 Poy  ....缅娜",
            "袁泉 Quan Yuan  ....建秋妻子",
            "江若琳 Elanne kwong  ....机场售票员",
            "吴廷烨 Berg Ng  ....益哥",
            "卢惠光 Ken Lo  ....Booby",
            "吴岱融 Doi-yung Ng  ....警署高层(行动)"
        ],
        "introduction": "从小一起长大的好兄弟马昊天（刘青云 饰）、张子伟（张家辉饰）和苏建秋（古天乐饰）共同效力于警队扫毒科。在一次临时改变计划的行动后，建秋因为卧底身份不能与妻子（袁泉饰）过正常生活而心生退意，但在阿天与子伟的劝说下，三人决定进行最后一搏。建秋跟着毒贩老大黑柴（林国斌饰）前往泰国与毒贩Bobby（卢惠光饰）进行对接，目的是见到行动的最大目标“八面佛”（卢海鹏饰），阿天则和子伟以及同事阿益（吴廷烨饰）进行跟进。由于泰国警方的配合不力导致建秋身份暴露，虽然建秋答应阿天继续把交易完成，但失败的导火索已经埋下。交易当天警方几乎全军覆没，危急之时阿天挟持了八面佛的女儿缅娜（宝儿饰）准备逃命，八面佛承诺只要还回缅娜阿天可以带走建秋和子伟中的一个，没被选中的则要被推进鳄鱼池，面对抉择阿天及进退两难……",
        "download_url": "ftp://ygdy8:ygdy8@d006.dygod.org:1113/[阳光电影www.ygdy8.com].扫毒.HD.720p.国语中字.rmvb",
        "content_url": "http://img226.poco.cn/mypoco/myphoto/20140124/21/66548034201401242109268624686417666_000.jpg"
    },
    {
        "teanslation_title": "金蝉脱壳/活人墓/越狱/钢铁坟墓(台)/逃亡大计(港)",
        "real_title": "Escape Plan",
        "time": "2013",
        "category": "动作/悬疑/惊悚",
        "language": "英语",
        "length": "1h 55mn",
        "director": "米凯尔·哈弗斯特罗姆 Mikael Håfström",
        "actors": [
            "西尔维斯特·史泰龙 Sylvester Stallone  ....Ray Breslin",
            "阿诺·施瓦辛格 Arnold Schwarzenegger  ....Rottmayer",
            "詹姆斯·卡维泽 James Caviezel  ....Willard Hobbes",
            "山姆·尼尔 Sam Neill  ....Dr. Emil Kaikev",
            "文森特·诺费奥 Vincent D'Onofrio  ....Lester Clark",
            "维尼·琼斯 Vinnie Jones  ....Drake",
            "50分 50 Cent  ....Hush",
            "艾米·莱安 Amy Ryan  ....Abigail Ross",
            "法兰·塔希尔 Faran Tahir  ....Javed",
            "马特·杰拉德 Matt Gerald  ....Roag"
        ],
        "introduction": "雷·布雷斯林（西尔维斯特·史泰龙 Sylvester Stallone 饰）是最强的越狱高手，曾在8年内成功逃出14座安全防卫工程最严密的重刑监狱。他的真正身份是美国国家安全局的监狱安管专家，每一次越狱成功，就代表他能找出该个监狱的安管漏洞，进而强化改善。",
        "download_url": "ftp://ygdy8:ygdy8@d201.dygod.org:9125/[阳光电影www.ygdy8.com].金蝉脱壳.BD.720p.中英双字幕.rmvb",
        "content_url": "http://img226.poco.cn/mypoco/myphoto/20140124/18/66548034201401241850354100038826062_001.jpg"
    },
    {
        "teanslation_title": "中学生圆山",
        "real_title": "Maruyama, the Middle Schooler",
        "time": "2013",
        "category": "喜剧/悬疑",
        "language": "日语",
        "length": "1h 59mn",
        "director": "宫藤官九郎 Kankur? Kud?",
        "actors": [
            "草剪刚 Tsuyoshi Kusanagi  ....下井辰夫",
            "平冈拓真 Takuma Hiraoka  ....丹山克也",
            "仲村彻 Toru Nakamura",
            "坂井真纪 Maki Sakai",
            "远藤贤司 Kenji Endo",
            "梁益俊 Ik-june Yang",
            "田口智朗 Tomorowo Taguchi",
            "You",
            "岩松了 Ry? Iwamatsu",
            "野波麻帆 Maho Nonami"
        ],
        "introduction": "相貌平平的男孩圆山克也（平冈拓真 饰），是每日过着两点一线平凡生活的初中二年级学生。他来自一个普通家庭，上班族父亲（仲村亨 饰）朝九晚五奔波，拙朴的母亲（坂井真纪 饰）疯狂痴迷韩剧，妹妹（锅本MM美 饰）反应迟钝，懵懂无知。正值青春期的圆山每天锻炼，追求一个柔软的身体。但正像这个年龄段的男孩一样，他如此锻炼的背后藏着不可告人的下流疯狂秘密。为了进入那个充满邪念的世界，笨蛋少年可谓无所不用其极。",
        "download_url": "ftp://ygdy8:ygdy8@d006.dygod.org:1112/[阳光电影www.ygdy8.com].中学生圆山.BD.720p.中文字幕.rmvb",
        "content_url": "http://img226.poco.cn/mypoco/myphoto/20140123/23/66548034201401232327304114388439197_001.jpg"
    },
    {
        "teanslation_title": "我为相亲狂",
        "real_title": "Dating Fever",
        "time": "2013",
        "category": "剧情",
        "language": "喜剧/爱情",
        "length": "106 mins",
        "director": "韩晶 Han Jing",
        "actors": [
            "杜海涛 Haitao Du  ....Tong Jun",
            "谢依霖 Sie Yi-Lin  ....Jiu Jiu",
            "韩雪 Cecilia Han  ....Bai Jingjing",
            "李佳航 Jiahang Li  ....Zhao Shuai",
            "冯铭潮 Feng Mingchao  ....Jiang Xiaoyu"
        ],
        "introduction": "美艳逼人，在一次相亲会上，富家子弟赵帅（李佳航 饰）被其风姿倾倒，主动搭讪遭拒，心有不甘的他使出浑身解数发动爱情攻势，结果惨败。戏痴啾啾（谢依霖饰）自编自演五个性格迥异的女孩，宅男江小鱼（冯铭潮 饰）在母亲遥控指挥下与之“地铁闪约”，上演了一出哭笑不得的相亲喜剧。频频相亲未果的童军（杜海涛饰）目睹此景，顿时被古灵精怪的啾啾所吸引，之前的童军由于在相亲过程中过于精明遭女方吐槽，啾啾的突然出现令他心中为之一震。其实，小鱼有个暗恋网友叫米雪（范玮琳饰），由于他自身性格的原因，与其一直保持若即若离的关系，迟迟未能踏出关键一步......",
        "download_url": "ftp://ygdy8:ygdy8@d201.dygod.org:9124/[阳光电影www.ygdy8.com].我为相亲狂.HD.720p.国语中字.mkv",
        "content_url": "http://img226.poco.cn/mypoco/myphoto/20140123/23/66548034201401232327304114388439197_000.jpg"
    },
    {
        "teanslation_title": "意外的恋爱时光",
        "real_title": "Love Speaks",
        "time": "2013",
        "category": "喜剧/爱情",
        "language": "普通话",
        "length": "1h 37mn",
        "director": "黎志 Zhi Li",
        "actors": [
            "房祖名 Jaycee Chan  ....周同",
            "郭采洁 Amber Kuo  ....王乐晴",
            "于莎莎 Yu Sha Sha",
            "钱入富 Ru-fu Qian",
            "康恩赫 Enhe Kang"
        ],
        "introduction": "单身女白领王乐晴（郭采洁饰）对生活期望很高，希望早日与男友邵东（高圣远饰）走上结婚的红毯。但p东是个工作狂，常常因工作忽视了自己的存在，乐晴不得已主动向男友求婚，并请周同（房祖名饰）拍摄她的求爱过程。搞视频工作室的周同愉快地接受了聘请，随乐晴踏上了求爱旅程，谁知一路上意外频发，迨虏欢稀Ｋ孀磐甘共苦的行程加码，周同对乐晴产生了异样的感觉。大龄剩女李晓玲（于莎莎饰）是乐晴的闺蜜，平日里嘴上没有把门儿的，属于典型的刀子嘴豆腐心，她以乐晴的爱情导师自居，对乐晴找对象看的比自己的事都重要，但她将怎样面对乐晴的婚变呢……",
        "download_url": "ftp://ygdy8:ygdy8@d006.dygod.org:1111/[阳光电影www.ygdy8.com].意外的恋爱时光.HD.720p.国语中字.rmvb",
        "content_url": "http://img226.poco.cn/mypoco/myphoto/20140122/21/66548034201401222157432732541291471_001.jpg"
    },
    {
        "teanslation_title": "非常父女档/钢筋男子/不接受退货",
        "real_title": "No se Aceptan Devoluciones/Instructions Not Included",
        "time": "2013",
        "category": "剧情/喜剧",
        "language": "西班牙语",
        "length": "2h:04m:16s",
        "director": "欧亨尼奥·德伯兹 Eugenio Derbez",
        "actors": [
            "艾赫尼奥·德伯兹 Eugenio Derbez  ....Valentín",
            "洛蕾托·佩拉尔塔 Loreto Peralta  ....Maggie",
            "杰西卡·林德赛 Jessica Lindsey  ....Julie",
            "Daniel Raymont  ....Frank Ryan",
            "Alessandra Rosaldo  ....Reneé",
            "雨果·史蒂格利茨 Hugo Stiglitz  ....Johnny Bravo",
            "Sammy Pérez  ....Sammy",
            "Arcelia Ramírez  ....Judeisy",
            "Agustín Bernal  ....Lupe",
            "Karla Olivares  ....Jackie"
        ],
        "introduction": "瓦伦丁是阿卡普尔科（墨西哥南部海滨度假城市）远近闻名的花花公子，直到有一天他发现某位旧情人把他们新出生的孩子扔在他家门口便消失之后，他的快活日子结束了。瓦伦丁带着孩子来到洛杉矶，起初是为了寻找孩子的母亲，结果只能和孩子两个人租了一间公寓在那里下来。孩子取名叫玛姬。六年过去了，玛姬渐渐长大，瓦伦丁也成为了好莱坞最受欢迎、薪水最高的特效演员之一，绰号“钢筋男子”。他总把玛姬带在身边，玛姬成了他的经纪人和片场指导。在抚养玛姬的过程中，瓦伦丁自己也渐渐学会了承担责任，他和女儿一起“长大”了。然而就在这个时候，玛姬的母亲却毫无征兆地突然出现，瓦伦丁害怕她会带走玛姬——玛姬不仅仅是他的女儿，而且是他最好的朋友。",
        "download_url": "ftp://ygdy8:ygdy8@d201.dygod.org:9123/[阳光电影www.ygdy8.com].非常父女档.BD.720p.中英双字幕.rmvb",
        "content_url": "http://img226.poco.cn/mypoco/myphoto/20140122/21/66548034201401222157432732541291471_000.jpg"
    },
    {
        "teanslation_title": "四大名捕2/四大名捕2：铁血天牢",
        "real_title": "The Four 2",
        "time": "2013",
        "category": "动作/悬疑/奇幻/武侠",
        "language": "普通话",
        "length": "116 mins",
        "director": "陈嘉上 Gordon Chan",
        "actors": [
            "邓超 Chao Deng  ....冷血",
            "刘亦菲 Yifei Liu  ....无情",
            "邹兆龙 Collin Chou  ....铁手",
            "郑中基 Ronald Cheng  ....追命",
            "黄秋生 Anthony Wong  ....诸葛正我",
            "江一燕 Yiyan Jiang  ....姬遥花",
            "吴秀波 Xiubo Wu  ....安世耿",
            "柳岩 Yan Liu  ....如烟",
            "成泰 Taishen Cheng  ....捕神",
            "邓萃雯 Shereen Tang  ....翠娘"
        ],
        "introduction": "多事的追命（郑中基 饰）、铁手（邹兆龙 饰）耍花招，撮合冷血（邓超 饰）、无情（刘亦菲饰）这对小情人，神侯府上下正其乐融融，空气却传来浓烈的血腥味道，三里之外的城郊老宅，杀人凶案正在发生！",
        "download_url": "ftp://ygdy8:ygdy8@d006.dygod.org:1110/[阳光电影www.ygdy8.com].四大名捕2.HD.720p.国语中字.rmvb",
        "content_url": "http://img226.poco.cn/mypoco/myphoto/20140121/23/66548034201401212323472858767129307_000.jpg"
    },
    {
        "teanslation_title": "饥饿游戏2：星火燎原/饥饿游戏2/饥饿游戏：燃烧的女孩/饥饿游戏：火星燎原",
        "real_title": "The Hunger Games: Catching Fire",
        "time": "2013",
        "category": "动作/科幻/惊悚/冒险",
        "language": "英语",
        "length": "2:27:31.842 (h:m:s.ms)",
        "director": "弗朗西斯·劳伦斯 Francis Lawrence",
        "actors": [
            "詹妮弗·劳伦斯 Jennifer Lawrence  ....凯妮丝·伊夫狄恩 Katniss Everdeen",
            "乔什·哈切森 Josh Hutcherson  ....皮塔·麦拉克 Peeta Mellark",
            "山姆·克拉弗林 Sam Claflin  ....芬尼克·欧戴尔 Finnick Odair",
            "吉娜·马隆 Jena Malone  ....乔安娜·梅森 Johanna Mason",
            "利亚姆·海姆斯沃斯 Liam Hemsworth  ....盖尔·霍桑 Gale Hawthorne",
            "唐纳德·萨瑟兰 Donald Sutherland  ....总统克里欧兰纽斯·斯诺 President Snow",
            "伍迪·哈里森 Woody Harrelson  ....黑密曲·阿伯纳西 Haymitch Abernathy",
            "伊丽莎白·班克斯 Elizabeth Banks  ....艾菲·纯科特 Effie Trinket",
            "蓝尼·克罗维兹 Lenny Kravitz  ....西纳 Cinna",
            "杰弗里·怀特 Jeffrey Wright  ....比特 Beetee"
        ],
        "introduction": "经历生死的凯特尼斯（詹妮弗·劳伦斯 Jennifer Lawrence 饰）和皮塔（乔什·哈切森 Josh Hutcherson 饰）得到了74届饥饿游戏冠军享有的一切待遇，但是两人的关系变得很尴尬，凯特尼斯无法放下昔日男友盖尔（利亚姆·海姆斯沃斯 Liam Hemsworth 饰），甚至还想要跟他远走高飞。凯特尼斯和皮塔越来越受到人民的欢迎，加上他俩假扮情侣的事情激怒了斯诺总统（唐纳德·萨瑟兰 Donald Sutherland 饰），他联合新的游戏设计师（菲利普·塞默·霍夫曼 Philip Seymour Hoffman 饰）开展了25年一届的“世界极限赛”，要求抽出12个区的历届男女冠军各一人参加，旨在杀死凯特尼斯。皮塔为了保护凯特尼斯，代替黑密曲（伍迪·哈里森 Woody Harrelson 饰）参赛，一对“恋人”又踏上了征程。在赛事中二人结交了不同区的盟友，同时皮塔继续对凯特尼斯表露真情，而她对皮塔的态度也有所变化，可惜事情并不像他们想象的一样，等待他们的只有阴谋。",
        "download_url": "ftp://ygdy8:ygdy8@d201.dygod.org:9122/[阳光电影www.ygdy8.com].饥饿游戏2：星火燎原.BD.720p.中英双字幕.rmvb",
        "content_url": "http://img226.poco.cn/mypoco/myphoto/20140121/15/66548034201401211547214055863621651_000.jpg"
    },
    {
        "teanslation_title": "年度之战：梦之队/BOTY世界Battle(台)/年度街舞大战",
        "real_title": "Battle of the Year: The Dream Team",
        "time": "2013",
        "category": "歌舞/剧情/音乐",
        "language": "英语",
        "length": "109 min",
        "director": "本森·李 Benson Lee",
        "actors": [
            "乔希·佩克 Josh Peck",
            "乔什·哈洛威 Josh Holloway  ....Derrek",
            "克里斯·布朗 Chris Brown",
            "拉兹·阿隆索 Laz Alonso  ....Dante",
            "Sawandi Wilson",
            "凯蒂·罗茨 Caity Lotz  ....Stacy",
            "Terrence Jenkins",
            "维罗妮卡·罗萨蒂 Weronika Rosati  ....Jolene",
            "Luis Rosado  ....Bambino",
            "Ivan 'Flipz' Velez  ....Flipz"
        ],
        "introduction": "由《迷失》男星乔什·哈洛威领衔主演的breaking竞赛片《年度之战：梦之队》根据2005年一群男孩参加奥林匹克大赛街舞\"年度之战\"的经历改编，讲述了乔什·哈洛威饰演的教练如何带领他的队伍夺魁的故事。影片街舞段落精彩纷呈，各种高技能动作轮番登场，电子乐炫目灯光将舞台范儿烘托的淋漓尽致，再加上本片将以3D形式上映，届时观众将如临比赛现场般体验电影中的动感跳跃。",
        "download_url": "ftp://ygdy8:ygdy8@d201.dygod.org:9119/[阳光电影www.ygdy8.com].年度街舞大战.BD.720p.中英双字幕.rmvb",
        "content_url": "http://img226.poco.cn/mypoco/myphoto/20140117/18/66548034201401171847211999584296386_001.jpg"
    },
    {
        "teanslation_title": "奥斯汀乐园",
        "real_title": "Austenland",
        "time": "2013",
        "category": "喜剧/爱情",
        "language": "英语",
        "length": "97 min",
        "director": "杰露莎·赫斯 Jerusha Hess",
        "actors": [
            "凯丽·拉塞尔 Keri Russell  ....Jane Hayes",
            "JJ·菲尔德 JJ Feild  ....Mr. Henry Nobley",
            "詹妮佛·库里奇 Jennifer Coolidge  ....Miss Elizabeth Charming",
            "布雷特·麦肯奇 Bret McKenzie  ....Martin",
            "乔治雅·金 Georgia King  ....Lady Amelia Heartwright",
            "詹姆斯·卡利斯 James Callis  ....Colonel Andrews",
            "简·西摩尔 Jane Seymour  ....Mrs. Wattlesbrook",
            "Ricky Whittle  ....Captain George East",
            "Silvia Crastan  ....Fun Fair Visitor",
            "Richard Reid  ....The Hot Servant"
        ],
        "introduction": "影片改编自英国作家Shannon Hale的同名小说，小说讲述一个30多岁的女人沉迷于简·奥斯汀小说塑造的“达西先生”，她认为现实中没有任何人能比得上达西先生。这位追求浪漫的女人现实中的爱情不断受挫，直到一封来自英国的邀请函彻底改变她的生活。",
        "download_url": "ftp://ygdy8:ygdy8@d006.dygod.org:1107/[阳光电影www.ygdy8.com].奥斯汀乐园.BD.720p.中英双字幕.rmvb",
        "content_url": "http://img226.poco.cn/mypoco/myphoto/20140118/23/66548034201401182258492590137643397_000.jpg"
    },
    {
        "teanslation_title": "弯刀杀戮/索女·重炮·神经刀(港)",
        "real_title": "Machete Kills",
        "time": "2013",
        "category": "动作/犯罪",
        "language": "英语/西班牙语",
        "length": "1h 47mn",
        "director": "罗伯特·罗德里格兹 Robert Rodriguez",
        "actors": [
            "丹尼·特乔 Danny Trejo  ....Machete Cortez",
            "艾梅柏·希尔德 Amber Heard  ....Miss San Antonio",
            "索菲娅·维加拉 Sofia Vergara  ....Madame Desdemona",
            "米歇尔·罗德里格兹 Michelle Rodriguez  ....Shé",
            "阿丽夏·维加 Alexa Vega  ....KillJoy",
            "杰西卡·阿尔芭 Jessica Alba  ....Sartana",
            "瓦妮莎·哈金斯 Vanessa Hudgens  ....Cereza",
            "梅尔·吉布森 Mel Gibson  ....Luther Voz",
            "女神卡卡 Lady GaGa  ....La Chameleón",
            "查理·辛 Charlie Sheen  ....U.S. President (as Carlos Estevez)"
        ],
        "introduction": "弯刀被美国ZF招募执行一项常人很难完成的任务，他必须要横穿墨西哥，擒获卡特尔组织的疯子头目，还有一个拥有太空武器并企图发起全球战争的武器狂人。与弯刀同行的还有一支军方队伍，他们将联合作战共同将无ZF主义计划瓦解掉。",
        "download_url": "ftp://ygdy8:ygdy8@d201.dygod.org:9118/[阳光电影www.ygdy8.com].弯刀杀戮.BD.720p.中英双字幕.rmvb",
        "content_url": "http://img226.poco.cn/mypoco/myphoto/20140117/18/66548034201401171847211999584296386_002.jpg"
    },
    {
        "teanslation_title": "乔布斯/贾伯斯(台)/乔布斯传",
        "real_title": "Jobs",
        "time": "2013",
        "category": "剧情/传记",
        "language": "英语",
        "length": "128 min",
        "director": "约书亚·迈克尔·斯坦恩 Joshua Michael Stern",
        "actors": [
            "艾什顿·库彻 Ashton Kutcher  ....Steve Jobs",
            "德蒙特·莫罗尼 Dermot Mulroney  ....Mike Markkula",
            "马修·莫迪恩 Matthew Modine  ....John Sculley",
            "詹姆斯·伍兹 James Woods  ....Jack Dudman",
            "J·K·西蒙斯 J.K. Simmons  ....Arthur Rock",
            "卢卡斯·哈斯 Lukas Haas  ....Daniel Kottke",
            "阿曼达·克鲁 Amanda Crew  ....Julie",
            "莱斯莉·安·华伦 Lesley Ann Warren  ....Clara Jobs",
            "乔什·盖德 Josh Gad  ....Steve Wozniak",
            "朗·埃达德 Ron Eldard  ....Rod Holt"
        ],
        "introduction": "故事从乔布斯（阿什顿·库彻 Ashton Kutcher 饰）自大学退学开始，他和友人斯蒂夫·盖瑞·沃兹尼亚克（乔什·盖德 Josh Gad 饰）有着同样的志向，两人因此共同合作，创建了苹果电脑。然而，随着苹果电脑的扩大，乔布斯和斯蒂夫·盖瑞·沃兹尼亚克不合拍之处越来越 多，导致日后乔布斯的愤而请辞，同时还挖走了一大票重要的人才……",
        "download_url": "ftp://ygdy8:ygdy8@d006.dygod.org:1106/[阳光电影www.ygdy8.com].乔布斯.BD.720p.中英双字幕.rmvb",
        "content_url": "http://img226.poco.cn/mypoco/myphoto/20140117/18/66548034201401171847211999584296386_003.jpg"
    },
    {
        "teanslation_title": "蠢蛋搞怪秀4：坏外公",
        "real_title": "Jackass Presents: Bad Grandpa",
        "time": "2013",
        "category": "剧情/喜剧",
        "language": "英语",
        "length": "102 min/92 min",
        "director": "杰夫·特雷梅恩 Jeff Tremaine",
        "actors": [
            "约翰尼·诺克斯维尔 Johnny Knoxville  ....Irving Zisman",
            "Georgina Cates  ....Kimmy",
            "Jackson Nicoll  ....Billy",
            "Blythe Barrington-Hughes  ....Pageant Contestant",
            "Zia Harris  ....Chuck",
            "Kamber Hejlik  ....Doctor",
            "Jill Kill  ....Pageant Reporter",
            "Madison Davis  ....Juggalo Girl",
            "George Faughnan  ....Juggalo Guy",
            "Grasie Mercedes  ....Hostess"
        ],
        "introduction": "约翰尼·诺克斯维尔饰演的男主角有个八岁的孙子，祖孙俩将开始一段横跨美国的旅程，一路上他们偷东西撞路牌婚礼葬礼四处搅局蠢事不断。",
        "download_url": "ftp://ygdy8:ygdy8@d201.dygod.org:9117/[阳光电影www.ygdy8.com].蠢蛋搞怪秀4：坏祖父.BD.720p.中英双字幕.rmvb",
        "content_url": "http://img226.poco.cn/mypoco/myphoto/20140116/23/66548034201401162322177031591961839_000.jpg"
    },
    {
        "teanslation_title": "维基解密/第五等级/第五阶层/泄密风云(港)",
        "real_title": "The Fifth Estate",
        "time": "2013",
        "category": "传记/剧情/惊悚",
        "language": "英语",
        "length": "128 Mins",
        "director": "比尔·康顿 Bill Condon",
        "actors": [
            "本尼迪克特·康伯巴奇 Benedict Cumberbatch  ....Julian Assange",
            "Daniel Brühl丹尼尔·布鲁赫 Daniel Brühl  ....Daniel Domscheit-Berg",
            "Alicia Vikander艾丽西卡·维坎德 Alicia Vikander  ....Anke",
            "Carice van Houten卡里斯·范·侯登 Carice van Houten  ....Birgitta Jónsdóttir",
            "Stanley Tucci斯坦利·图齐 Stanley Tucci  ....James Boswell",
            "Laura Linney劳拉·琳妮 Laura Linney  ....Sarah Shaw",
            "Anthony Mackie安东尼·麦凯 Anthony Mackie  ....Sam Coulson",
            "Dan Stevens丹·史蒂文斯 Dan Stevens  ....Ian Katz",
            "David Thewlis大卫·休里斯 David Thewlis  ....Nick Davies",
            "Peter Capaldi彼得·卡帕尔蒂 Peter Capaldi  ....Alan Rusbridger"
        ],
        "introduction": "本尼迪克特·康伯巴奇饰演“维基解密”创始人朱利安·保罗·阿桑奇（Julian Paul Assange）。维基解密是一个大型文档泄露及分析网站，曾经在2010年公开了多达9.2万份的驻阿美军秘密文件而引起轩然大波。康伯巴奇将要饰演的朱利安·保罗·阿桑奇是网站的董事与发言人，曾主修过物理、数学，做过程序员和黑客。阿桑奇本人和网站一样都备受争议，他曾经因为解密工作获得过多项荣誉，也曾收到过国际刑警组织的逮捕令。2010年阿桑奇因涉嫌在瑞典强奸及性侵犯2名女性被通缉，2010年12月7日他向伦敦警方自首，随即被押送到威斯敏斯特地方法院出席引渡聆讯，保释申请被驳回。2012年8月16日，阿桑奇获厄瓜多尔政治庇护。",
        "download_url": "ftp://ygdy8:ygdy8@d006.dygod.org:1105/[阳光电影www.ygdy8.com].危机解密.BD.720p.中英双字幕.rmvb",
        "content_url": "http://img226.poco.cn/mypoco/myphoto/20140115/20/66548034201401152002113904563071258_000.jpg"
    },
    {
        "teanslation_title": "囚徒/俘虏/私法争锋(台)/罪迷宫(港)",
        "real_title": "Prisoners/Vangid/Zatvorenici",
        "time": "2013",
        "category": "犯罪/剧情/惊悚",
        "language": "英语",
        "length": "153 Mins",
        "director": "丹尼斯·维勒弗 Denis Villeneuve",
        "actors": [
            "休·杰克曼 Hugh Jackman  ....Keller",
            "杰克·吉伦哈尔 Jake Gyllenhaal  ....Detective Loki",
            "保罗·达诺 Paul Dano",
            "维奥拉·戴维斯 Viola Davis  ....Nancy Birch",
            "梅丽莎·里奥 Melissa Leo",
            "玛丽亚·贝罗 Maria Bello  ....Grace Dover",
            "泰伦斯·霍华德 Terrence Dashon Howard",
            "Fred Griffith  ....Groggy Man",
            "Jeff Pope  ....Scott Milland",
            "Dylan Minnette  ....Ralph Dover"
        ],
        "introduction": "住在小镇的木匠凯勒（休·杰克曼饰）的六岁女儿安娜，以及她朋友乔伊一同失踪了，两对父母心中的恐惧可想而知。唯一的线索，是在孩子们失踪之前，停在同一条街上的一辆破旧的休旅车。负责侦办此案的警探罗基逮捕了休旅车的主人艾利斯，但却因为没有充足的证据，而在四十八小时之后，依法将他释放。",
        "download_url": "ftp://ygdy8:ygdy8@d201.dygod.org:9116/[阳光电影www.ygdy8.com].囚徒.BD.720p.中英双字幕.rmvb",
        "content_url": "http://img226.poco.cn/mypoco/myphoto/20140115/16/66548034201401151654482031289563191_000.jpg"
    },
    {
        "teanslation_title": "蓝色茉莉/情迷蓝茉莉(港)/蓝色茉莉花",
        "real_title": "Blue Jasmine",
        "time": "2013",
        "category": "剧情/喜剧",
        "language": "英语",
        "length": "98 min",
        "director": "伍迪·艾伦 Woody Allen",
        "actors": [
            "凯特·布兰切特 Cate Blanchett  ....Jasmine",
            "亚历克·鲍德温 Alec Baldwin  ....Hal",
            "莎莉·霍金斯 Sally Hawkins  ....Ginger",
            "鲍比·坎纳瓦尔 Bobby Cannavale  ....Chili",
            "Joy Carlin  ....Woman on Plane",
            "Richard Conti  ....Woman's Husband",
            "Glen Caspillo  ....Cab Driver",
            "查理·塔汗 Charlie Tahan  ....Young Danny",
            "坦米·布兰查德 Tammy Blanchard  ....Jasmine's Friend Jane",
            "艾米莉·博格尔 Emily Bergl  ....Hal and Jasmine's Friend"
        ],
        "introduction": "纽约的名媛茉莉和她富商丈夫之间的婚姻亮起了红灯，眼见爱情面和经济面都濒临重大危机，茉莉决定搬到旧金山，住进妹妹金洁的一般公寓，重新开始过一个和以前大大不同的生活。",
        "download_url": "ftp://ygdy8:ygdy8@d006.dygod.org:1104/[阳光电影www.ygdy8.com].蓝色茉莉.BD.720p.中英双字幕.rmvb",
        "content_url": "http://img226.poco.cn/mypoco/myphoto/20140114/22/66548034201401142210372908933243339_000.jpg"
    },
    {
        "teanslation_title": "风暴",
        "real_title": "Firestorm",
        "time": "2013",
        "category": "动作/犯罪",
        "language": "普通话",
        "length": "1h 45mn",
        "director": "袁锦麟 Alan Yuen",
        "actors": [
            "刘德华 Andy Lau  ....吕明哲",
            "姚晨 Chen Yao  ....罗燕冰",
            "林家栋 Ka Tung Lam  ....陶成邦",
            "胡军 Jun Hu  ....曹楠",
            "吕良伟 Ray Lui  ....啪哥",
            "姜皓文 Patrick Keung  ....唐强",
            "黄德斌 Kenny Wong  ....警探",
            "梁烈唯 Oscar Leung  ....燕冰弟弟",
            "唐文龙 Michael Tong  ....阿豹",
            "施祖南 Vincent Sze"
        ],
        "introduction": "吕明哲（刘德华 饰）是香港屡破大案的高级督察，陶成邦（林家栋 饰）是屡教不改刚出狱的街头混混。吕明哲在一次街头对峙悍匪头目曹楠（胡军饰）已占上风时，被儿时的好友陶成邦搅局。面对犯罪团伙的不断挑衅，吕明哲誓言不惜一切代价将其一锅端，警匪双方的杀戮游戏正式开始。",
        "download_url": "ftp://ygdy8:ygdy8@d201.dygod.org:9114/[阳光电影www.ygdy8.com].风暴.HD.720p.国语中字.rmvb",
        "content_url": "http://img226.poco.cn/mypoco/myphoto/20140113/23/66548034201401132333203273484112296_000.jpg"
    }
]