[
    {
        "teanslation_title": "颠倒黑白",
        "real_title": "The Reverse",
        "time": "2009",
        "category": "剧情/喜剧/爱情/惊悚",
        "language": "波兰语",
        "length": "1h 35m 51s",
        "director": "Borys Lankosz",
        "actors": [
            "Agata Buzek ...  Sabina Jankowska",
            "Krystyna Janda ...  Irena Jankowska - Sabina's mother",
            "Anna Polony ...  Sabina's grandmother",
            "Marcin Dorocinski ...  Bronislaw Falski",
            "Adam Woronowicz ...  Mr. Józef",
            "Bronislaw Wroclawski ...  Barski - publishing house manager",
            "Lukasz Konopka ...  Arkadiusz 'Arkadek' Jankowski - Sabina's brother",
            "Blazej Wójcik ...  Poet Marcel Wodzicki",
            "Jerzy Bonczak ...  Dostojnik Zygmunt",
            "Jacek Poniedzialek ...  Dostojnik"
        ],
        "introduction": "影片以黑色幽默的方式呈现了1950年的波兰社会。",
        "download_url": "ftp://dygod1:dygod1@d092.dygod.org:2861/颠倒黑白DVD中英双字/[电影天堂www.dy2018.net]颠倒黑白DVD中英双字.rmvb",
        "content_url": "http://photo6.zxip.com/albums6/folder18/14186/20110201122217/2011241840416451.jpg"
    },
    {
        "teanslation_title": "预产期/临盆急先疯/临门凑一脚(台)",
        "real_title": "Due Date",
        "time": "2010",
        "category": "喜剧",
        "language": "英语",
        "length": "117 Mins",
        "director": "托德·菲利普斯 Todd Phillips",
        "actors": [
            "小罗伯特·唐尼 Robert Downey Jr.  ....Peter Highman",
            "扎克·加利费安纳基斯 Zach Galifianakis  ....Ethan Tremblay / Ethan Chase",
            "米歇尔·莫娜汉 Michelle Monaghan  ....Sarah Highman",
            "杰米·福克斯 Jamie Foxx  ....Darryl",
            "朱丽叶特·刘易斯 Juliette Lewis  ....Heidi",
            "丹尼·麦克布耐德 Danny McBride  ....Lonnie",
            "RZA  ....Airport Screener",
            "Matt Walsh  ....TSA Agent",
            "Brody Stevens  ....Limo Driver",
            "Jakob Ulrich  ....Patrick"
        ],
        "introduction": "小罗伯特·唐尼在片中饰演一个即将当爸爸的人，他全力驱车回家准备迎接孩子的出生，而在这个旅程中，却有着扎克饰演的一个不搭调的伙伴结伴同行。",
        "download_url": "ftp://dygod1:dygod1@d038.dygod.org:2264/预产期DVD中英双字/[电影天堂www.dy2018.net]预产期DVD中英双字.rmvb",
        "content_url": "http://photo6.zxip.com/albums6/folder18/14186/20110201122217/20112295131262.jpg"
    },
    {
        "teanslation_title": "灵异医院",
        "real_title": "Psych 9",
        "time": "2010",
        "category": "神秘/惊悚/恐怖",
        "language": "英语",
        "length": "1:38:01",
        "director": "安德鲁·肖特尔 Andrew Shortell",
        "actors": [
            "莎拉·福斯特 Sara Foster  ....Roslyn",
            "加利·艾尔维斯 Cary Elwes  ....Dr. Clement",
            "迈克尔·比恩 Michael Biehn  ....Det. Marling",
            "加布埃尔·玛恩 Gabriel Mann  ....Cole",
            "考林·加普 Colleen Camp  ....Beth",
            "雯特·艾娃·佐莉 Winter Ave Zoli  ....Emma",
            "苏西·阿米 Susie Amy  ....Anne Marks",
            "Katherine Shanklin  ....Young Roslyn",
            "Joel Kirby  ....Henry Mar",
            "taobao"
        ],
        "introduction": "影片《灵异医院》讲述的是一个有着不堪过去的女人在一家新近倒闭关门的医院找到了一份核对病人简历复印件的工作，而孤独一人在隔绝的医院值夜班的过程中她经历了一些神秘事件。有所警觉的她通过这些事件发现医院可能和近日出现的谋杀案有关，而要破解这些谜团，首先她需要仔细梳理一下自己混乱的过去。",
        "download_url": "ftp://dygod1:dygod1@d606.dygod.org:4037/灵异医院.[中英双字.1024分辨率]/[电影天堂www.dy2018.net]灵异医院BD中英双字.rmvb",
        "content_url": "http://photo6.zxip.com/albums6/folder18/14186/20110201122217/2011211222551549.jpg"
    },
    {
        "teanslation_title": "死亡空间：余波/死亡空间：劫后余生/死亡空间：后果",
        "real_title": "Dead Space: Aftermath",
        "time": "2011",
        "category": "动画/科幻/恐怖",
        "language": "英语",
        "length": "1h:17mn",
        "director": "Mike Disa",
        "actors": [
            "克里斯托弗·加吉 Christopher Judge ….Nick Kuttner (voice)",
            "Peter Woodward ….Lead Interrogator (voice)",
            ""
        ],
        "introduction": "时空背景设定在2509年，地球不只与USG石村号（USG Ishimura）和伊萨克．克拉克失去了联系，同时也与派去救援他们的USB欧班农号（USB OBannon）失联。欧班农号上有四名船员存活了下来，但是没有人知道其他成员的下落，也没有人知道他们遇上了什么事情，更没有人知道他们究竟隐藏了什么样的秘密。这一切的一切，全都将透过《余波》来揭晓！",
        "download_url": "ftp://dygod1:dygod1@d092.dygod.org:2859/死亡空间：余波.[中英双字.1024分辨率]/[电影天堂www.dy2018.net]死亡空间：余波BD中英双字.rmvb",
        "content_url": "http://photo4.zxip.com/albums4/folder18/14184/20110102135517/201113118420478.jpg"
    },
    {
        "teanslation_title": "杰克去划船/为爱疯狂/纽约奇缘",
        "real_title": "Jack Goes Boating",
        "time": "2010",
        "category": "爱情/喜剧",
        "language": "英语",
        "length": "89 mins",
        "director": "菲利普·塞默·霍夫曼 Philip Seymour Hoffman",
        "actors": [
            "菲利普·塞默·霍夫曼 Philip Seymour Hoffman  ....Jack",
            "艾米·莱安 Amy Ryan  ....Connie",
            "约翰·奥提兹 John Ortiz  ....Clyde",
            "Elizabeth Rodriguez  ....Event Coordinator",
            "达芬妮·鲁宾-维佳 Daphne Rubin-Vega  ....Lucy",
            "Harry L. Seddon  ....Teacher",
            "Stephen Adly-Guirgis  ....MTA Worker",
            "James P. Anderson  ....Pool Swimmer",
            "Paul Thornton  ....Chauffeur",
            "Richard Petrocelli  ....Uncle Frank"
        ],
        "introduction": "在一个冬天，豪华轿车驾驶员杰克（菲利普·塞默·霍夫曼 饰）有了自己事业上的新想法，同时，他业余的大部分时间都与他的挚友克莱德（约翰·奥提兹 饰）和克莱德的妻子露西（达芬妮·鲁宾-维佳 饰）一同度过。克莱德夫妇热心的将露西的同事康妮（艾米·莱安 饰）介绍给了杰克认识，而在于康妮的交往中，杰克也激起了对生活的热情，他学习厨艺，找到了新的工作，又向克莱德学习游泳，希望能给康妮一个她想要的浪漫的游船旅行。而正当杰克和康妮情投意合时，克莱德和露西的婚姻却开始崩溃，于是，这两对伴侣不得不陷入一场犹豫和踌躇的对情感和生活的思考中。",
        "download_url": "ftp://dygod1:dygod1@d057.dygod.org:1228/杰克去划船.[中英双字.1024分辨率]/[电影天堂www.dy2018.net]杰克去划船BD中英双字.rmvb",
        "content_url": "http://photo4.zxip.com/albums4/folder18/14184/20110102135517/2011130111831396.jpg"
    },
    {
        "teanslation_title": "灵动：鬼影实录2/鬼入镜(未分级版)",
        "real_title": "Paranormal Activity 2",
        "time": "2010",
        "category": "恐怖/神秘/惊悚",
        "language": "英语",
        "length": "97 minutes",
        "director": "托德·威廉姆斯 Tod Williams",
        "actors": [
            "凯蒂·菲德斯通 Katie Featherston...Katie",
            "加布里埃尔·约翰逊 Gabriel Johnson...Raphael Omen / Demon Killer (uncredited)"
        ],
        "introduction": "还是在那间危机重重的屋子里，又出现了更加不可思议的怪事。似乎有恶魔存在，又有人被恶魔附体，真相究竟是什么？",
        "download_url": "ftp://dygod1:dygod1@d082.dygod.org:1074/灵动：鬼影实录2.[中英双字.1024分辨率]/[电影天堂www.dy2018.net]灵动：鬼影实录2BD中英双字.rmvb",
        "content_url": "http://photo4.zxip.com/albums4/folder18/14184/20110102135517/201113011181875.jpg"
    },
    {
        "teanslation_title": "僵尸新战士",
        "real_title": "Vampire Warriors",
        "time": "2010",
        "category": "动作/奇幻/惊悚/喜剧",
        "language": "普通话/粤语",
        "length": "100 Min",
        "director": "罗守耀 Dennis Law",
        "actors": [
            "元华 Wah Yuen",
            "蒋璐霞 Luxia Jiang  ....阿丫",
            "钱小豪 Siu-hou Chin",
            "周秀娜 Chrissie Chow",
            "卢颂之 Dada Lo  ....阿嘉",
            "熊欣欣 Xin Xin Xiong",
            "张文慈 Pinky Cheung  ....阿索",
            "林熹瞳 Rachel Lam  ....阿碧",
            "纪焕博 Rock",
            "裴殷 A lin  ....阿Lin"
        ],
        "introduction": "自古以来，在这个看似平凡的人类世界，暗里活著一群共居者-吸血僵尸。少年僵尸猎人阿丫（蒋璐霞）独居在一废置屠房。与不害人的良善僵尸阿斯（周秀娜）阿隆（钱小豪）及阿力（纪焕博）一家为好邻居。神秘大僵尸阿盟（元华）忽然在这本来太平无事的世界出现。凶猛的阿盟残杀僵尸同类。阿丫的家姐阿素（张文慈）及阿斯的好友阿嘉（卢颂之），阿LIN（斐殷）和阿碧（林熹瞳）亦相继被阿盟所害。杀机终於来到废置屠房。阿盟先杀掉阿隆和阿力，然后再追杀阿丫及阿斯。在走无退路的处境之下，阿电影图册(17张)丫为了复仇及杀掉为害人间的阿盟。为了和阿盟决一死战，阿丫决定牺牲自己，甘愿被阿斯一咬变成强尸。阿丫与阿盟这终极一战，打出＂僵尸世界真功夫！",
        "download_url": "ftp://dygod1:dygod1@d038.dygod.org:3140/[电影天堂www.dy2018.net]僵尸新战士.1024x576.国粤双语.中文字幕.mkv",
        "content_url": "http://photo4.zxip.com/albums4/folder18/14184/20110102135517/2011129109162766.jpg"
    },
    {
        "teanslation_title": "60号高地之下",
        "real_title": "Beneath Hill 60",
        "time": "2010",
        "category": "剧情/历史/战争",
        "language": "英语",
        "length": "118 minutes",
        "director": "杰瑞米·西姆斯 Jeremy Sims",
        "actors": [
            "杰奎琳·麦根斯 Jacqueline McKenzie  ....Emma Waddell",
            "杰拉德·勒帕斯基 Gerald Lepkowski  ....William Waddell",
            "阿登·杨 Aden Young  ....Major Brady North",
            "布伦丹·考威尔 Brendan Cowell  ....Captain Oliver Woodward",
            "盖东·格兰特利 Gyton Grantley  ....Norman Morris",
            "哈里森·吉尔伯特森 Harrison Gilbertson  ....Frank Tiffin",
            "Isabella Heathcote  ....Marjorie Waddell",
            "Steve Le Marquand  ....Sergeant Bill Fraser",
            "Anthony Hayes  ....Captain William McBride",
            "Leon Ford  ....Lieutenant Robert Clayton"
        ],
        "introduction": "奥利弗伍德沃德的非凡真实故事。这是1916年，德沃德泪别他的年轻女友，从军前往西部前线，其间还要穿越德国阵地。德沃德和他的团队从事秘密隧道工事，铺设炸药。他们的努力将改变战争的进程。",
        "download_url": "ftp://dygod1:dygod1@d057.dygod.org:1227/60号高地之下.[中英双字.1024分辨率]/[电影天堂www.dy2018.net]60号高地之下BD中英双字.rmvb",
        "content_url": "http://photo4.zxip.com/albums4/folder18/14184/20110102135517/201112910917121.jpg"
    },
    {
        "teanslation_title": "致命伴旅/机密邂逅(港)/色遇(台)/游客/致命伴侣",
        "real_title": "The Tourist",
        "time": "2010",
        "category": "剧情/动作/惊悚",
        "language": "英语",
        "length": "103 Mins",
        "director": "弗洛里安·亨克尔·冯·多纳斯马 Florian Henckel von Donnersmarck",
        "actors": [
            "约翰尼·德普 Johnny Depp  ....Frank Tupelo",
            "安吉丽娜·朱莉 Angelina Jolie  ....Elise Clifton-Ward",
            "保罗·贝坦尼 Paul Bettany  ....Inspector John Acheson",
            "提摩西·道尔顿 Timothy Dalton  ....Chief Inspector Jones",
            "史蒂文·伯克夫 Steven Berkoff  ....Reginald Shaw",
            "卢夫斯·塞维尔 Rufus Sewell  ....The Englishman",
            "克里斯蒂安·德·西卡 Christian De Sica  ....Colonnello Lombardi",
            "阿莱西奥·博尼 Alessio Boni  ....Sergente Cerato",
            "Daniele Pecci  ....Tenente Narduzzi",
            "Giovanni Guidelli  ....Tenente Tommassini"
        ],
        "introduction": "一个男人去海边度假时，邂逅了一位美丽的神秘女子。在短暂的美好时光后，女子却突然失踪，一个重大的阴谋也悄然降临到了男人的身上。",
        "download_url": "ftp://dygod1:dygod1@d606.dygod.org:4036/致命伴旅/[电影天堂www.dy2018.net]致命伴旅DVDR5中英双字.rmvb",
        "content_url": "http://econo-soft.com/uploads/posts/2010-12/1292683373471tourist.jpeg"
    },
    {
        "teanslation_title": "怪兽/异兽禁区",
        "real_title": "Monsters",
        "time": "2010",
        "category": "剧情/科幻/爱情",
        "language": "英语",
        "length": "1:33:59",
        "director": "加里斯·爱德华斯 Gareth Edwards",
        "actors": [
            "艾伦·尼布洛 Allan Niblo  ....producer",
            "詹姆斯·理查森 James Richardson  ....producer",
            "Jim Spencer  ....line producer",
            "尼克·拉夫 Nick Love  ....executive producer",
            "Rupert Preston  ....executive producer",
            "Nigel Williams  ....executive producer"
        ],
        "introduction": "这个骇人的故事源于六年前，一艘NASA探测船，载有含有未知威胁性的外星生物样本返回地球，不幸的是，抵达之际，竟意外坠毁于墨西哥。",
        "download_url": "ftp://dygod1:dygod1@d082.dygod.org:1073/怪兽.[中英双字.1024分辨率]/[电影天堂www.dy2018.net]怪兽BD中英双字.rmvb",
        "content_url": "http://photo4.zxip.com/albums4/folder18/14184/20110102135517/2011128123946200.jpg"
    },
    {
        "teanslation_title": "遭遇陌生人/你将会遇到一个又高又黑的陌生人/遇上陌生情人(港)/命中注定,遇见爱(台)",
        "real_title": "You Will Meet a Tall Dark Stranger",
        "time": "2010",
        "category": "喜剧/爱情",
        "language": "英语",
        "length": "98 min",
        "director": "伍迪·艾伦 Woody Allen",
        "actors": [
            "安东尼·霍普金斯 Anthony Hopkins  ....Alfie",
            "娜奥米·沃茨 Naomi Watts  ....Sally",
            "乔什·布洛林 Josh Brolin  ....Roy",
            "安东尼奥·班德拉斯 Antonio Banderas  ....Greg",
            "盖玛·琼斯 Gemma Jones  ....Helena Shepridge",
            "芙蕾达·平托 Freida Pinto  ....Dia",
            "露茜·彭奇 Lucy Punch  ....Charmaine",
            "Roger Ashton-Griffiths  ....Jonathan",
            "艾文·布莱纳 Ewen Bremner  ....Henry Strangler",
            "宝林·科林斯 Pauline Collins  ....Cristal Delgiorno"
        ],
        "introduction": "安东尼·霍普金斯和盖玛·琼斯扮演一对老夫妻阿尔菲和海伦娜,在阿尔菲离开自己并与年轻的应召女郎查尔梅陷(露茜·彭奇饰)入爱河后,海伦特则失去了理智,将自己的生活全部交给了一个夸夸其谈的占卜师。他们的女儿萨莉(娜奥米·沃茨饰)的婚姻也不幸福,她最近迷上了画廊老板格雷格(安东尼奥·班德拉斯饰)。萨莉的老公罗伊(乔什·布洛林饰)是位小说家,他最近正紧张地等待着出版社对他最新的小说的回应,与此同时,他对附近遇到的一位神秘女子迪亚(芙蕾达·平托饰)想入非非。",
        "download_url": "ftp://dygod1:dygod1@d092.dygod.org:2857/遭遇陌生人.[中字.1024分辨率]/[电影天堂www.dy2018.net]遭遇陌生人BD中字.rmvb",
        "content_url": "http://photo4.zxip.com/albums4/folder18/14184/20110102135517/20111272316135105.jpg"
    },
    {
        "teanslation_title": "明日，战争爆发时/明日战争爆发",
        "real_title": "Tomorrow When The War Began",
        "time": "2010",
        "category": "动作/冒险/剧情",
        "language": "英语",
        "length": "104 min",
        "director": "斯图尔特·比蒂 Stuart Beattie",
        "actors": [
            "凯特琳·斯塔西 Caitlin Stasey....Ellie Linton",
            "蕾切儿·哈伍德 Rachel Hurd-Wood....Corrie Mackenzie",
            "丹尼兹·阿克丹尼兹 Deniz Akdeniz....Homer Yannos",
            "菲比·托金 Phoebe Tonkin....Fiona Maxwell",
            "林肯·刘易斯 Lincoln Lewis....Kevin Holmes",
            "艾什利·康宁斯 Ashleigh Cummings....Robyn Mathers",
            "克里斯·彭 Chris Pang....Lee Takkam",
            "安德鲁·瑞恩 Andrew Ryan....Chris Lang (as Andy Ryan)",
            "Matthew Dale ....Mr. Coles",
            "Masa Yamaguchi ....Sergeant"
        ],
        "introduction": "影片讲述7名高中生到一个偏远的小镇远足露营，回到家时发现澳大利亚已经陷入战争，他们不得不拿起武器展开反击……",
        "download_url": "ftp://dygod1:dygod1@d057.dygod.org:2025/明日，战争爆发时.[中字.1024分辨率]/[电影天堂www.dy2018.net]明日，战争爆发时BD中字.rmvb",
        "content_url": "http://photo4.zxip.com/albums4/folder18/14184/20110102135517/20111262119431221.jpg"
    },
    {
        "teanslation_title": "危情时速/煞破天劫(港)/煞不住",
        "real_title": "Unstoppable",
        "time": "2010",
        "category": "动作/剧情/惊悚",
        "language": "英语",
        "length": "96 Mins",
        "director": "托尼·斯科特 Tony Scott",
        "actors": [
            "丹泽尔·华盛顿 Denzel Washington...Frank Barnes",
            "克里斯·派恩 Chris Pine...Will Colson",
            "罗莎里奥·道森 Rosario Dawson...Connie Hooper",
            "伊桑·苏普利 Ethan Suplee",
            "洁西·斯克拉姆 Jessy Schram...Darcy Colson",
            "凯文·杜恩 Kevin Dunn",
            "伊丽莎白·马瑟斯 Elizabeth Mathis...Nicole",
            "凯文·查普曼 Kevin Chapman...Bunny",
            "大卫·沃肖夫斯基 David Warshofsky...Jud",
            "Meagan Tandy...Maya"
        ],
        "introduction": "与许多虚构的动作大片不同，这个故事由真实事件改编。威尔·科尔森（克里斯·派恩 饰演）是新来的列车长，将在1206号火车上工作。资深铁路工程师弗兰克·巴恩斯（丹佐尔·华盛顿 饰演）负责威尔的培训工作。他告诉威尔，这个工作需要高度注意力和正确的判断力，稍有差池就会酿出大祸。在培训的过程中，弗兰克突然收到消息，得知一辆无人驾驶的列车正在高速向他们驶来，车上装载有整整八箱、数千吨重的有毒化学物品，相当于一枚导弹的摧毁力量，足够瞬间炸平一幢大楼。当地的政府部门采取了各种应急措施，却都无法阻止这辆失控的列车。眼看它飞速驶入人口密集的地区，并迎向一辆搭载着150名小学生的火车。弗兰克和威尔决定孤注一掷，亲自前往现场，阻止列车的前行…",
        "download_url": "ftp://dygod1:dygod1@d038.dygod.org:1222/危情时速.[中英双字.1024分辨率]/[电影天堂www.dy2018.net]危情时速BD中英双字.rmvb",
        "content_url": "http://photo4.zxip.com/albums4/folder18/14184/20110102135517/20111262119395560.jpg"
    },
    {
        "teanslation_title": "怪兽/异兽禁区",
        "real_title": "Monsters",
        "time": "2010",
        "category": "剧情/科幻/爱情",
        "language": "英语",
        "length": "1:33:59",
        "director": "加里斯·爱德华斯 Gareth Edwards",
        "actors": [
            "艾伦·尼布洛 Allan Niblo  ....producer",
            "詹姆斯·理查森 James Richardson  ....producer",
            "Jim Spencer  ....line producer",
            "尼克·拉夫 Nick Love  ....executive producer",
            "Rupert Preston  ....executive producer",
            "Nigel Williams  ....executive producer"
        ],
        "introduction": "这个骇人的故事源于六年前，一艘NASA探测船，载有含有未知威胁性的外星生物样本返回地球，不幸的是，抵达之际，竟意外坠毁于墨西哥。",
        "download_url": "ftp://dygod1:dygod1@d322.dygod.org:7011/怪兽DVD中英双字/[电影天堂www.dy2018.net]怪兽DVD中英双字.rmvb",
        "content_url": "http://photo4.zxip.com/albums4/folder18/14184/20110102135517/20111262119423584.jpg"
    },
    {
        "time": "2010",
        "category": "动作/战争/恐怖",
        "language": "法语",
        "length": "1h:39mn",
        "director": "雨果·马丁 Hugues Martin",
        "actors": [
            "格雷戈瓦·勒普兰斯-林盖 Grégoire Leprince-Ringuet  ....Michel",
            "提艾利·弗雷蒙 Thierry Frémont  ....Vacard",
            "塞瑞尔·拉菲利 Cyril Raffaelli  ....Louvier",
            "Stéphane Debac  ....Durieux",
            "Matthias Van Khache  ....Malovitch",
            "Grégory Quidel  ....Max",
            "Emmanuel Bonami  ....Ballant",
            "Omar Lotfi  ....Ka",
            "taobao",
            "mel"
        ],
        "introduction": "1960年的阿尔及利亚。一队法国伞兵被送往阿尔及利亚的沙漠腹地寻找一架失事飞机。很快，他们确定了飞机残骸的位置，但没有发现任何生还者，只找到了一只印有“秘密抵抗”字样的手提箱。伞兵队遭到敌军袭击，他们躲进了一个废弃的城堡，然而却不顾当地守护者的提醒，吵醒了穆斯林的神灵，一个沙漠中不祥的幽灵……",
        "download_url": "ftp://dygod1:dygod1@d082.dygod.org:2053/沙漠迷城.[中字.1024分辨率]/[电影天堂www.dy2018.net]沙漠迷城BD中字.rmvb",
        "content_url": "http://photo4.zxip.com/albums4/folder18/14184/20110102135517/20111262119403060.jpg"
    },
    {
        "teanslation_title": "灵动：鬼影实录2/鬼入镜(未分级版)",
        "real_title": "Paranormal Activity 2",
        "time": "2010",
        "category": "恐怖/神秘/惊悚",
        "language": "英语",
        "length": "97 minutes",
        "director": "托德·威廉姆斯 Tod Williams",
        "actors": [
            "凯蒂·菲德斯通 Katie Featherston...Katie",
            "加布里埃尔·约翰逊 Gabriel Johnson...Raphael Omen / Demon Killer (uncredited)"
        ],
        "introduction": "还是在那间危机重重的屋子里，又出现了更加不可思议的怪事。似乎有恶魔存在，又有人被恶魔附体，真相究竟是什么？",
        "download_url": "ftp://dygod1:dygod1@d606.dygod.org:4035/灵动：鬼影实录2DVD中英双字/[电影天堂www.dy2018.net]灵动：鬼影实录2DVD中英双字.rmvb",
        "content_url": "http://photo4.zxip.com/albums4/folder18/14184/20110102135517/2011125232692078.jpg"
    },
    {
        "teanslation_title": "巴阿里亚/巴格里亚/巴格里亚：风之门/风之门：情系西西里岛",
        "real_title": "Baaria",
        "time": "2009",
        "category": "喜剧/剧情/历史/战争",
        "language": "西西里语/意大利语/英语",
        "length": "144 mins",
        "director": "朱塞佩·托纳多雷 Giuseppe Tornatore",
        "actors": [
            "玛格丽特·玛德 Margaret Madè  ....Mannina",
            "弗兰切斯克·齐亚纳 Frances Scianna  ....Peppino",
            "莫妮卡·贝鲁奇 Monica Bellucci",
            "雷欧·波瓦 Raoul Bova  ....Giornalista Romano",
            "安吉拉·摩琳娜 ángela Molina",
            "恩里克·洛维索 Enrico Lo Verso",
            "妮可·吉玛多 Nicole Grimaudo",
            "劳拉·齐亚蒂 Laura Chiatti",
            "加布里埃莱·拉维亚 Gabriele Lavia",
            "阿尔多 Aldo  ....(as Aldo Baglio)"
        ],
        "introduction": "巴阿里亚（Barria）是西西里岛巴勒莫省最大的城市巴格里亚（Bagheria）在西西里方言中的叫法，本片通过当地一家三代人自上世纪三十年代开始自六十年代为止的种种生活变迁，展示了意大利在两次世界大战期间以及其后所经历过的重大历史变革，在影片中人们可以看到当时意大利所发生的种种政治变动，从法西斯到共 产 党，从基督教民主党到社 会 主 义，各种政治风潮在意大利国内交替上演，并影响着一代又一代意大利普通人的生活。",
        "download_url": "ftp://dygod1:dygod1@d092.dygod.org:2856/巴阿里亚DVD中英双字/[电影天堂www.dy2018.net]巴阿里亚DVD中英双字-cd1.rmvb",
        "content_url": "http://photo4.zxip.com/albums4/folder18/14184/20110102135517/2011125232672235.jpg"
    },
    {
        "teanslation_title": "美版生人勿进/生人勿进/噬血童话/吸血儿凶",
        "real_title": "Let Me In",
        "time": "2010",
        "category": "爱情/奇幻/惊悚/剧情/恐怖",
        "language": "英语",
        "length": "107 Min",
        "director": "马特·里夫斯 Matt Reeves",
        "actors": [
            "柯蒂·斯密特-麦菲 Kodi Smit-McPheeKodi....Owen",
            "科洛·莫瑞兹 Chloe Moretz....Abby",
            "理查·詹金斯 Richard Jenkins....The Father",
            "Jimmy 'Jax' Pinchak ....Mark",
            "萨莎·巴瑞斯 Sasha Barrese....Virginia",
            "Chris Browning ....Jack",
            "卡拉·布欧诺 Cara Buono....Owen's Mother",
            "伊莱亚斯·科泰斯 Elias Koteas....The Policeman",
            "塞斯·艾德金斯 Seth Adkins....Seth",
            "Rachel Hroncich ....Admitting Nurse"
        ],
        "introduction": "剧情",
        "download_url": "ftp://dygod1:dygod1@d082.dygod.org:1072/美版生人勿进.[中英双字.1024分辨率]/[电影天堂www.dy2018.net]美版生人勿进BD中英双字.rmvb",
        "content_url": "http://photo4.zxip.com/albums4/folder18/14184/20110102135517/2011125114949980.jpg"
    },
    {
        "teanslation_title": "爱情与灵药/爱上医药代表/爱以及其他上瘾的药/爱情药不药/爱情恋上瘾",
        "real_title": "Love And Other Drugs",
        "time": "2010",
        "category": "喜剧/爱情",
        "language": "英语",
        "length": "112 mins",
        "director": "爱德华·兹威克 Edward Zwick",
        "actors": [
            "杰克·吉伦哈尔 Jake Gyllenhaal  ....Jamie Randall",
            "安妮·海瑟薇 Anne Hathaway  ....Maggie Murdock",
            "奥利弗·普莱特 Oliver Platt  ....Bruce Winston",
            "汉克·阿扎利亚 Hank Azaria  ....Dr. Stan Knight",
            "乔什·盖德 Josh Gad  ....Josh Randall",
            "盖布瑞·马赫特 Gabriel Macht  ....Trey Hannigan",
            "朱迪·格雷尔 Judy Greer  ....Cindy",
            "乔治·席格 George Segal  ....Dr. James Randall",
            "吉尔·克雷伯格 Jill Clayburgh  ....Nancy Randall",
            "皮特·弗雷德曼 Peter Friedman  ....California Man"
        ],
        "introduction": "故事讲述甜美女孩玛姬（安妮·海瑟薇 饰）其实是一名帕金森症患者，原本打算“潇洒”过完余下生命的她却遇上了在女人中左右逢源的伟哥销售员杰米（杰克·吉伦哈尔 饰）。两人关系的突飞猛进令两位当事人都感到吃惊，“保持距离”的准则似乎也不起作用了，爱情正如灵药改变深陷其中的他们……",
        "download_url": "ftp://dygod1:dygod1@d038.dygod.org:2262/爱情与灵药.[中字.1024分辨率]/[电影天堂www.dy2018.net]爱情与灵药BD中字.rmvb",
        "content_url": "http://photo4.zxip.com/albums4/folder18/14184/20110102135517/20111251417341134.jpg"
    },
    {
        "teanslation_title": "街角的小王子/街角小王子",
        "real_title": "In Case of Love/Jie Jiao De Xiao Wang Zi",
        "time": "2010",
        "category": "剧情",
        "language": "普通话",
        "length": "77 Min",
        "director": "林孝谦 Xiaoqian Lin",
        "actors": [
            "杨佑宁 Tony Yang",
            "郭碧婷 Biting Guo",
            "叶羿君 Jaline Yeh",
            "李至正 Zhizheng Li",
            "杨子珊 Zishan Yang",
            "林辰唏 Lin Chen-Xi",
            "汤志伟 Chih Wei Tang",
            "李芸婵 Robin Lee"
        ],
        "introduction": "一只街角的小猫咪，悄悄地改变了两人的命运。真实世界里，她是气质沉静的美术系学生，但在虚拟的网路空间中，她则是一笔一笔画着猫咪故事的超人气图文画家。而他则是摇滚乐团的吉他手，乐声中有着难以言说的忧郁。",
        "download_url": "ftp://dygod1:dygod1@d092.dygod.org:2855/街角小王子DVD/[电影天堂www.dy2018.net]街角小王子DVD中字.rmvb",
        "content_url": "http://photo4.zxip.com/albums4/folder18/14184/20110102135517/20111241614132020.jpg"
    },
    {
        "teanslation_title": "小海龟大历险/塞米的历险：秘密通道/环球世界五十年",
        "real_title": "Sammys Adventure The Secret Passage",
        "time": "2010",
        "category": "动画/冒险",
        "language": "英语",
        "length": "85min",
        "director": "本·斯塔森 Ben Stassen",
        "actors": [
            "伊莎贝拉·弗尔曼 Isabelle Fuhrman  ....Hatchling Shelly",
            "詹尼·麦卡锡 Jenny McCarthy  ....(voice)",
            "蒂姆·克里 Tim Curry  ....(voice)",
            "梅兰尼·格里菲斯 Melanie Griffith  ....(voice)",
            "安东尼·安德森 Anthony Anderson  ....(voice)",
            "小艾德·博格里 Ed Begley Jr.  ....(voice)",
            "斯泰西·基齐 Stacy Keach  ....(voice)",
            "凯西·格里芬 Kathy Griffin  ....(voice)",
            "柯斯汀·科佩尔 Kierstin Koppel",
            "比利·安格 Billy Unger  ....Hatchling Sammy (voice)"
        ],
        "introduction": "本片讲述的是在当今全球变暖的趋势下，一只在1959年孵化而出的海龟用50年的时间环游世界。",
        "download_url": "ftp://dygod1:dygod1@d082.dygod.org:2052/小海龟大历险.[中字.1024分辨率]/[电影天堂www.dy2018.net]小海龟大历险BD中字.rmvb",
        "content_url": "http://photo4.zxip.com/albums4/folder18/14184/20110102135517/2011124161412880.jpg"
    },
    {
        "teanslation_title": "危情时速/煞破天劫(港)/煞不住",
        "real_title": "Unstoppable",
        "time": "2010",
        "category": "动作/剧情/惊悚",
        "language": "英语",
        "length": "96 Mins",
        "director": "托尼·斯科特 Tony Scott",
        "actors": [
            "丹泽尔·华盛顿 Denzel Washington...Frank Barnes",
            "克里斯·派恩 Chris Pine...Will Colson",
            "罗莎里奥·道森 Rosario Dawson...Connie Hooper",
            "伊桑·苏普利 Ethan Suplee",
            "洁西·斯克拉姆 Jessy Schram...Darcy Colson",
            "凯文·杜恩 Kevin Dunn",
            "伊丽莎白·马瑟斯 Elizabeth Mathis...Nicole",
            "凯文·查普曼 Kevin Chapman...Bunny",
            "大卫·沃肖夫斯基 David Warshofsky...Jud",
            "Meagan Tandy...Maya"
        ],
        "introduction": "与许多虚构的动作大片不同，这个故事由真实事件改编。威尔·科尔森（克里斯·派恩 饰演）是新来的列车长，将在1206号火车上工作。资深铁路工程师弗兰克·巴恩斯（丹佐尔·华盛顿 饰演）负责威尔的培训工作。他告诉威尔，这个工作需要高度注意力和正确的判断力，稍有差池就会酿出大祸。在培训的过程中，弗兰克突然收到消息，得知一辆无人驾驶的列车正在高速向他们驶来，车上装载有整整八箱、数千吨重的有毒化学物品，相当于一枚导弹的摧毁力量，足够瞬间炸平一幢大楼。当地的政府部门采取了各种应急措施，却都无法阻止这辆失控的列车。眼看它飞速驶入人口密集的地区，并迎向一辆搭载着150名小学生的火车。弗兰克和威尔决定孤注一掷，亲自前往现场，阻止列车的前行…",
        "download_url": "ftp://dygod1:dygod1@d038.dygod.org:2261/危情时速.[中字.1024分辨率]/[电影天堂www.dy2018.net]危情时速BD中字.rmvb",
        "content_url": "http://photo4.zxip.com/albums4/folder18/14184/20110102135517/2011124161416750.jpg"
    },
    {
        "teanslation_title": "爱你一万年",
        "real_title": "Love You 10000 Years/Love of Ten Thousand Years",
        "time": "2010",
        "category": "剧情/爱情",
        "language": "普通话/日语",
        "length": "108 Min",
        "director": "北村丰晴",
        "actors": [
            "周渝民 Vic Zhou",
            "加藤侑纪 Youki Kato",
            "纳豆 Yuzhi Lin",
            "王月 Yue Wang",
            "黄镫辉 Denghui Huang",
            "李伯恩 Boen Li",
            "朱蕾安 Leian Zhu",
            "郝蕾 Lei Hao"
        ],
        "introduction": "《爱你一万年》是一部充满欢乐的青春喜剧，内容是一名外派来台湾工作的曰本女生，与一个台客摇滚歌手爱情冤家的故事。",
        "download_url": "ftp://dygod1:dygod1@d092.dygod.org:3357/爱你一万年DVD/[电影天堂www.dy2018.net]爱你一万年DVD中字-cd1.rmvb",
        "content_url": "http://photo4.zxip.com/albums4/folder18/14184/20110102135517/20111241614111127.jpg"
    },
    {
        "teanslation_title": "127小时",
        "real_title": "127 Hours",
        "time": "2010",
        "category": "剧情",
        "language": "英语",
        "length": "93 Min",
        "director": "丹尼·鲍尔 Danny Boyle",
        "actors": [
            "詹姆斯·弗兰科 James Franco....Aron Ralston",
            "凯特·玛拉 Kate Mara....Kristi",
            "爱波·塔布琳 Amber Tamblyn....Megan",
            "Sean Bott ....Aron's Friend (as Sean A. Bott)",
            "Koleman Stinger ....Aron Age 5",
            "特里特·威廉斯 Treat Williams....Aron's Dad",
            "John Lawrence ....Brion",
            "凯特·伯顿 Kate Burton....Aron's Mom",
            "Parker Hadley ....Aron Age 15",
            "克蕾曼丝·波西 Clemence Poesy....Rana"
        ],
        "introduction": "远足者阿伦·罗斯顿（詹姆斯·弗朗哥 舀饰）在犹他州的一次远足中，因为在一个偏僻的峡谷被掉落的山石压住胳膊而无法动弹，孤独的被困在那里。在接下来的五天里，罗斯顿精神上经受着巨大的考验，同时也审视着自己的人生，更重要的是，他需要利用手上的各种条件想法脱离险境。终于，他痛下决心，以惊人的勇气给自己的胳膊做了截肢手术，并攀下65英尺的谷底，同时忍痛步行8公里后，最后获得营救，成功生还。",
        "download_url": "ftp://dygod1:dygod1@d606.dygod.org:4034/127小时/[电影天堂www.dy2018.net]127小时DVDscr中字.rmvb",
        "content_url": "http://photo4.zxip.com/albums4/folder18/14184/20110102135517/2011123163931118.jpg"
    },
    {
        "teanslation_title": "国王的演讲",
        "real_title": "The Kings Speech",
        "time": "2010",
        "category": "剧情/历史",
        "language": "英语",
        "length": "119 Min",
        "director": "汤姆·霍伯 Tom Hooper",
        "actors": [
            "科林·费斯 Colin Firth  ....King George VI",
            "海伦娜·伯翰·卡特 Helena Bonham Carter  ....Queen Elizabeth",
            "杰弗里·拉什 Geoffrey Rush  ....Lionel Logue",
            "迈克尔·刚本 Michael Gambon  ....King George V",
            "盖·皮尔斯 Guy Pearce  ....King Edward VIII",
            "德里克·雅各比 Derek Jacobi  ....Archbishop Cosmo Lang",
            "Robert Portal  ....Equerry",
            "Richard Dixon  ....Private Secretary",
            "Paul Trussell  ....Driver for The House of Windsor",
            "Adrian Scarborough  ....BBC Radio Announcer"
        ],
        "introduction": "影片讲述了英国女王伊丽莎白二世的父亲乔治六世国王的故事。乔治六世就是那位为了美人而放弃江山的爱德华八世的弟弟，爱德华退位后，他很不情愿地坐上了国王的宝座。然而乔治六世有很严重的口吃，发表讲话时非常吃力，连几句很简单的话都结结巴巴地讲不出来。幸运的是他遇到了语言治疗师莱昂纳尔（Lionel Logue），通过一系列的训练两人成为好友，国王的口吃也大为好转，随后他发表了著名的圣诞讲话，鼓舞了当时二战中的英国军民。",
        "download_url": "ftp://dygod1:dygod1@d038.dygod.org:1221/国王的演讲/[电影天堂www.dy2018.net]国王的演讲DVDscr中英双字-cd1.rmvb",
        "content_url": "http://photo4.zxip.com/albums4/folder18/14184/20110102135517/2011123163929344.jpg"
    }
]